LICENSE.txt
setup.py
setupbundle.py
MathBench.egg-info/PKG-INFO
MathBench.egg-info/SOURCES.txt
MathBench.egg-info/dependency_links.txt
MathBench.egg-info/entry_points.txt
MathBench.egg-info/requires.txt
MathBench.egg-info/top_level.txt
artwork/LICENSE.txt
artwork/mathbench-big.png
artwork/mathbench.icns
artwork/mathbench.ico
artwork/mathbench.png
artwork/mathbench.svg
doc/doc-basic-usage.rst
doc/doc-development.rst
doc/doc-editor-work.rst
doc/doc-features.rst
doc/doc-install.rst
doc/doc-library-use.rst
doc/doc-plugins.rst
doc/index.rst
doc/mathbench.css
doc/images/mathbench_lin_librarydesk.png
doc/images/mathbench_lin_pluginactivate.png
doc/images/mathbench_lin_pluginarchive.png
doc/images/mathbench_lin_pluginconfig.png
doc/images/mathbench_lin_sessiontoscript.png
doc/images/mathbench_lin_shell_completion.png
doc/images/mathbench_lin_shell_exec.png
doc/images/mathbench_lin_shell_pythonpower.png
doc/images/mathbench_win_launchscript_detail.png
mathbench/MathBench.py
mathbench/__init__.py
mathbench/basement/__init__.py
mathbench/basement/configuration.py
mathbench/basement/history_manager.py
mathbench/basement/librarian.py
mathbench/basement/logging_utils.py
mathbench/basement/plugin_manager.py
mathbench/ext/__init__.py
mathbench/ext/columnsizer.py
mathbench/ext/pluginmanagement_widgets.py
mathbench/lab/__init__.py
mathbench/lab/advisor.py
mathbench/lab/apparatus.py
mathbench/lab/fumehood.py
mathbench/lab/lab_settings.py
mathbench/lab/labbench.py
mathbench/lab/library.py
mathbench/lab/logbook.py
mathbench/lab/notebook.py
utils/math2app.sh
