Metadata-Version: 1.0
Name: MathBench
Version: 1.1.0
Summary: Not a whole lab, just a small bench...
Home-page: http://mathbench.sourceforge.net
Author: Thibauld Nion
Author-email: tibonihoo @at@  yahoo .dot. fr
License: BSD
Keywords: editor shell documentation math script IDE
Platform: All
Classifier: Development Status :: 4 - Beta
Classifier: Intended Audience :: Education
Classifier: Intended Audience :: End Users/Desktop
Classifier: Intended Audience :: Science/Research
Classifier: Intended Audience :: Developers
Classifier: License :: OSI Approved :: BSD License
Classifier: Operating System :: OS Independent
Classifier: Programming Language :: Python
Classifier: Topic :: Scientific/Engineering
Classifier: Topic :: Scientific/Engineering :: Information Analysis
Classifier: Topic :: Scientific/Engineering :: Mathematics
Classifier: Topic :: Text Editors :: Integrated Development Environments (IDE)
Classifier: Topic :: Software Development :: Libraries :: Python Modules
